opinionated_mcp/__init__.py
opinionated_mcp/auth.py
opinionated_mcp/crypto.py
opinionated_mcp/routes.py
opinionated_mcp/server.py
opinionated_mcp/tests/__init__.py
opinionated_mcp/tests/test_auth.py
opinionated_mcp/tests/test_crypto.py
opinionated_mcp/tests/test_init.py
opinionated_mcp/tests/test_routes.py
opinionated_mcp/tests/test_server.py
opinionated_mcp-2025.6.28.7596.dist-info/METADATA
opinionated_mcp-2025.6.28.7596.dist-info/WHEEL
opinionated_mcp-2025.6.28.7596.dist-info/entry_points.txt
opinionated_mcp-2025.6.28.7596.dist-info/top_level.txt
opinionated_mcp-2025.6.28.7596.dist-info/RECORD
