Metadata-Version: 2.4
Name: opinionated_mcp
Version: 2025.6.28.7596
Summary: An opinionated MCP framework
Author-email: Moshe Zadka <moshez@zadka.club>
License: Permission is hereby granted, free of charge, to any person obtaining a
Project-URL: Homepage, https://github.com/moshez/opinionated_mcp
Requires-Dist: fastapi
Requires-Dist: uvicorn
Requires-Dist: httpx
Requires-Dist: cryptography
Requires-Dist: mcp
Requires-Dist: starlette
Requires-Dist: itsdangerous
Provides-Extra: tests
Requires-Dist: virtue; extra == "tests"
Requires-Dist: pyhamcrest; extra == "tests"
Requires-Dist: coverage; extra == "tests"
Requires-Dist: respx; extra == "tests"
Provides-Extra: mypy
Requires-Dist: mypy; extra == "mypy"
Provides-Extra: lint
Requires-Dist: flake8; extra == "lint"
Requires-Dist: black; extra == "lint"
Provides-Extra: docs
Requires-Dist: sphinx; extra == "docs"
